dodecahedron/__init__.py
dodecahedron/cli.py
dodecahedron/config.py
dodecahedron/errors.py
dodecahedron/handlers.py
dodecahedron/helpers.py
dodecahedron/json.py
dodecahedron/messagebroker.py
dodecahedron/messagebus.py
dodecahedron/queues.py
dodecahedron/settings.py
dodecahedron/dispatchers/__init__.py
dodecahedron/dispatchers/abstract_dispatcher.py
dodecahedron/dispatchers/progressive_dispatcher.py
dodecahedron/listeners/__init__.py
dodecahedron/listeners/abstract_listener.py
dodecahedron/listeners/redis_listener.py
dodecahedron/mappers/__init__.py
dodecahedron/mappers/abstract_mapper.py
dodecahedron/mappers/class_mapper.py
dodecahedron/mappers/dictionary_mapper.py
dodecahedron/mappers/schema.py
dodecahedron/messages/__init__.py
dodecahedron/messages/command.py
dodecahedron/messages/event.py
dodecahedron/messages/message.py
dodecahedron/metaclasses/__init__.py
dodecahedron/metaclasses/message.py
dodecahedron/metaclasses/repository.py
dodecahedron/metaclasses/singleton.py
dodecahedron/metaclasses/tracker.py
dodecahedron/models/__init__.py
dodecahedron/models/abstract_models.py
dodecahedron/progress/__init__.py
dodecahedron/progress/abstract_progress_bar.py
dodecahedron/progress/tqdm_progress_bar.py
dodecahedron/publishers/__init__.py
dodecahedron/publishers/abstract_publisher.py
dodecahedron/publishers/redis_publisher.py
dodecahedron/repositories/__init__.py
dodecahedron/repositories/abstract_repository.py
dodecahedron/repositories/csv_repository.py
dodecahedron/repositories/eventful_repository.py
dodecahedron/repositories/file_system_repository.py
dodecahedron/repositories/sessioned_repository.py
dodecahedron/repositories/sqlalchemy_repository.py
dodecahedron/repositories/txt_repository.py
dodecahedron/repositories/xlsx_repository.py
dodecahedron/testing/__init__.py
dodecahedron/testing/repositories.py
dodecahedron/testing/units_of_work.py
dodecahedron/units_of_work/__init__.py
dodecahedron/units_of_work/abstract_unit_of_work.py
dodecahedron-0.0.5.dist-info/METADATA
dodecahedron-0.0.5.dist-info/WHEEL
dodecahedron-0.0.5.dist-info/licenses/LICENSE
dodecahedron-0.0.5.dist-info/RECORD
